bbscraper/__init__.py
bbscraper/__main__.py
bbscraper/cli.py
bbscraper/scraper.py
bbscraper/urls.py
bbscraper-1.2.dist-info/entry_points.txt
bbscraper-1.2.dist-info/LICENSE
bbscraper-1.2.dist-info/WHEEL
bbscraper-1.2.dist-info/METADATA
bbscraper-1.2.dist-info/RECORD
