Metadata-Version: 2.1
Name: bbscraper
Version: 1.2
Summary: bbscraper
Home-page: https://github.com/anderson89marques/PyFixedFlatFile
License: UNKNOWN
Author: Anderson Marques
Author-email: andersonoanjo18@gmail.com
Maintainer: anderson89marques
Requires-Python: >=3.6
Classifier: Development Status :: 5 - Production/Stable
Classifier: Environment :: Console
Classifier: Intended Audience :: Financial and Insurance Industry
Classifier: License :: OSI Approved :: GNU Lesser General Public License v3 (LGPLv3)
Classifier: Natural Language :: Portuguese (Brazilian)
Classifier: Programming Language :: Python :: 3.6
Classifier: Programming Language :: Python :: 3 :: Only
Classifier: Topic :: Office/Business :: Financial :: Accounting
Classifier: Topic :: Utilities
